process_videos/__init__.py
process_videos/cli.py
process_videos-0.2.4.dist-info/licenses/LICENSE
process_videos-0.2.4.dist-info/METADATA
process_videos-0.2.4.dist-info/WHEEL
process_videos-0.2.4.dist-info/entry_points.txt
process_videos-0.2.4.dist-info/top_level.txt
process_videos-0.2.4.dist-info/RECORD
