Metadata-Version: 2.4
Name: process-videos
Version: 0.2.4
Summary: Batch video processor with audio normalization and ffmpeg compression
Home-page: https://github.com/Obadowski/process-videos
Author: Vinicius Obadowski
Author-email: you@example.com
Project-URL: Bug Tracker, https://github.com/Obadowski/process-videos/issues
Project-URL: Source Code, https://github.com/Obadowski/process-videos
Keywords: ffmpeg video audio batch normalization cli loudnorm
Classifier: Development Status :: 4 - Beta
Classifier: Environment :: Console
Classifier: Intended Audience :: End Users/Desktop
Classifier: Intended Audience :: Developers
Classifier: License :: OSI Approved :: MIT License
Classifier: Operating System :: OS Independent
Classifier: Programming Language :: Python :: 3
Classifier: Programming Language :: Python :: 3.7
Classifier: Topic :: Multimedia :: Video
Classifier: Topic :: Utilities
Requires-Python: >=3.7
License-File: LICENSE
Requires-Dist: click
Requires-Dist: imageio-ffmpeg
Dynamic: author
Dynamic: author-email
Dynamic: classifier
Dynamic: description
Dynamic: description-content-type
Dynamic: home-page
Dynamic: keywords
Dynamic: license-file
Dynamic: project-url
Dynamic: requires-dist
Dynamic: requires-python
Dynamic: summary
